killer/__init__.py
killer/__main__.py
killer/killer.py
killer/killer_base.py
killer/killer_config.json
killer/killer_posix.py
killer/killer_windows.py
killer/posix/__init__.py
killer/posix/power.py
killer/utils/__init__.py
killer/utils/log.py
killer/windows/__init__.py
killer/windows/power.py
killer-0.7.1.dist-info/LICENSE
killer-0.7.1.dist-info/METADATA
killer-0.7.1.dist-info/WHEEL
killer-0.7.1.dist-info/entry_points.txt
killer-0.7.1.dist-info/top_level.txt
killer-0.7.1.dist-info/zip-safe
killer-0.7.1.dist-info/RECORD
