Metadata-Version: 2.1
Name: killer
Version: 0.7.1
Summary: Shuts the system down upon disallowed changes
Home-page: https://github.com/Lvl4Sword/Killer
Author: Lvl4Sword, GhostOfGoes, MarkKoz
License: AGPL 3.0
Project-URL: Discord Server, https://discord.gg/bTRxxMJ
Project-URL: IRC, https://webchat.freenode.net/?channels=%23killer
Keywords: killer,kill,watch,watchdog,monitoring,monitor,tamper,tampering,tamper-evident,shutdown,poweroff
Platform: Linux
Platform: Windows
Classifier: Development Status :: 3 - Alpha
Classifier: Environment :: Console
Classifier: License :: OSI Approved :: GNU Affero General Public License v3
Classifier: Operating System :: Microsoft :: Windows
Classifier: Operating System :: Microsoft :: Windows :: Windows 10
Classifier: Operating System :: Microsoft :: Windows :: Windows 8.1
Classifier: Operating System :: Microsoft :: Windows :: Windows 8
Classifier: Operating System :: Microsoft :: Windows :: Windows 7
Classifier: Operating System :: POSIX
Classifier: Operating System :: POSIX :: Linux
Classifier: Programming Language :: Python
Classifier: Programming Language :: Python :: 3
Classifier: Programming Language :: Python :: 3.5
Classifier: Programming Language :: Python :: 3.6
Classifier: Programming Language :: Python :: 3.7
Classifier: Programming Language :: Python :: 3 :: Only
Classifier: Programming Language :: Python :: Implementation :: CPython
Classifier: Intended Audience :: Developers
Classifier: Intended Audience :: System Administrators
Classifier: Intended Audience :: Information Technology
Classifier: Topic :: System :: Systems Administration
Classifier: Topic :: System :: Networking :: Monitoring :: Hardware Watchdog
Classifier: Topic :: System :: Monitoring
Classifier: Topic :: System
Classifier: Topic :: Utilities
Requires-Python: >=3.5
Requires-Dist: pywin32 (>=223) ; platform_system == "Windows"
